setup.cfg
setup.py
my_custom_lib/__init__.py
my_custom_lib/operators.py
my_custom_lib.egg-info/PKG-INFO
my_custom_lib.egg-info/SOURCES.txt
my_custom_lib.egg-info/dependency_links.txt
my_custom_lib.egg-info/top_level.txt