Metadata-Version: 2.1
Name: my-custom-lib
Version: 0.1.0
Summary: A simple math library for basic operations
Home-page: https://github.com/PVPSMILE/my_custom_lib.git
Author: PVPSMILE
Author-email: frank01zeroy@gmail.com
License: MIT
Platform: UNKNOWN
Classifier: Programming Language :: Python :: 3
Classifier: License :: OSI Approved :: MIT License
Classifier: Operating System :: OS Independent
Requires-Python: >=3.6
